README.md
setup.cfg
setup.py
cso_ansible_sdk/__init__.py
cso_ansible_sdk/api.py
cso_ansible_sdk/constants.py
cso_ansible_sdk/error_report.py
cso_ansible_sdk/errors.py
cso_ansible_sdk.egg-info/PKG-INFO
cso_ansible_sdk.egg-info/SOURCES.txt
cso_ansible_sdk.egg-info/dependency_links.txt
cso_ansible_sdk.egg-info/requires.txt
cso_ansible_sdk.egg-info/top_level.txt